arm/avhclient/__init__.py
arm/avhclient/__main__.py
arm/avhclient/avh_backend.py
arm/avhclient/avh_cli.py
arm/avhclient/avh_client.py
arm/avhclient/aws_backend.py
arm/avhclient/helper.py
arm/avhclient/local_backend.py
arm_avhclient-0.1.10.dist-info/LICENSE
arm_avhclient-0.1.10.dist-info/METADATA
arm_avhclient-0.1.10.dist-info/WHEEL
arm_avhclient-0.1.10.dist-info/entry_points.txt
arm_avhclient-0.1.10.dist-info/top_level.txt
arm_avhclient-0.1.10.dist-info/RECORD
