Metadata-Version: 2.1
Name: arm-avhclient
Version: 0.1.10
Summary: Arm Virtual Hardware Command Line Interface
Home-page: https://github.com/ARM-software/avhclient
Author: Samuel Pelegrinello Caipers, Jonatan Antoni
Author-email: Samuel.PelegrinelloCaipers@arm.com, Jonatan.Antoni@arm.com
Classifier: Development Status :: 5 - Production/Stable
Classifier: Intended Audience :: Developers
Classifier: License :: OSI Approved :: Apache Software License
Classifier: Natural Language :: English
Classifier: Operating System :: OS Independent
Classifier: Programming Language :: Python
Classifier: Programming Language :: Python :: 3
Classifier: Programming Language :: Python :: 3.8
Classifier: Programming Language :: Python :: 3.9
Classifier: Programming Language :: Python :: 3.10
Classifier: Topic :: Software Development :: Build Tools
Requires-Python: >=3.8
License-File: LICENSE
Requires-Dist: boto3 (~=1.20)
Requires-Dist: botocore (~=1.20)
Requires-Dist: PyYAML (~=6.0)
Requires-Dist: semantic-version (~=2.9)
Provides-Extra: dev
Requires-Dist: coverage (~=6.2) ; extra == 'dev'
Requires-Dist: python-dateutil (~=2.8) ; extra == 'dev'
Requires-Dist: pylint (~=2.14) ; extra == 'dev'
Requires-Dist: restructuredtext-lint (~=1.3) ; extra == 'dev'
Requires-Dist: setuptools (~=59.4) ; extra == 'dev'
Requires-Dist: unittest-xml-reporting (~=3.0) ; extra == 'dev'
